systempath/__init__.py
systempath/i systempath.py
systempath-1.2.2.dist-info/LICENSE
systempath-1.2.2.dist-info/METADATA
systempath-1.2.2.dist-info/WHEEL
systempath-1.2.2.dist-info/top_level.txt
systempath-1.2.2.dist-info/RECORD
